{
    "fluentMethods": true,
    "relationships": [
        {
            "relationshipType": "one-to-one",
            "relationshipName": "concerned",
            "otherEntityName": "booking",
            "ownerSide": false,
            "otherEntityRelationshipName": "concerns"
        }
    ],
    "fields": [
        {
            "fieldName": "model",
            "fieldType": "String",
            "fieldValidateRules": [
                "required"
            ]
        },
        {
            "fieldName": "type",
            "fieldType": "String",
            "fieldValidateRules": [
                "required"
            ]
        },
        {
            "fieldName": "regNumber",
            "fieldType": "String",
            "fieldValidateRules": [
                "required"
            ]
        },
        {
            "fieldName": "available",
            "fieldType": "Boolean",
            "fieldValidateRules": [
                "required"
            ]
        }
    ],
    "changelogDate": "20180307123729",
    "entityTableName": "car",
    "dto": "mapstruct",
    "pagination": "pagination",
    "service": "serviceImpl",
    "jpaMetamodelFiltering": false
}